CHANGES.rst
MANIFEST.in
README.rst
setup.py
src/monprojet/__init__.py
src/monprojet.egg-info/PKG-INFO
src/monprojet.egg-info/SOURCES.txt
src/monprojet.egg-info/dependency_links.txt
src/monprojet.egg-info/not-zip-safe
src/monprojet.egg-info/requires.txt
src/monprojet.egg-info/top_level.txt