Metadata-Version: 1.1
Name: monprojet
Version: 1.0.0
Summary: Un projet de démo
Home-page: http://pypi.python.org/pypi/monprojet
Author: Gilles Lenfant
Author-email: gilles.lenfant@alterway.fr
License: GPLv3
Platform: UNKNOWN
Classifier: Programming Language :: Python
Classifier: License :: OSI Approved :: GNU General Public License v3 (GPLv3)
